radinNFP/__init__.py
radinNFP-2.5.1.dist-info/METADATA
radinNFP-2.5.1.dist-info/WHEEL
radinNFP-2.5.1.dist-info/top_level.txt
radinNFP-2.5.1.dist-info/RECORD
