Metadata-Version: 2.1
Name: radinNFP
Version: 2.5.1
Summary: nfp calculator for Polygons
Author: Radin-CO
Classifier: Programming Language :: Python :: 3
Classifier: License :: OSI Approved :: MIT License
Classifier: Operating System :: OS Independent
Requires-Dist: numpy
